universalasync/__init__.py
universalasync/py.typed
universalasync/utils.py
universalasync/version.py
universalasync/wrapper.py
universalasync-0.5.0.0.dist-info/METADATA
universalasync-0.5.0.0.dist-info/WHEEL
universalasync-0.5.0.0.dist-info/licenses/LICENSE
universalasync-0.5.0.0.dist-info/RECORD
