Metadata-Version: 2.4
Name: universalasync
Version: 0.5.0.0
Summary: A library to help automate the creation of universal python libraries
Project-URL: Homepage, https://github.com/bitcart/universalasync
Project-URL: Source, https://github.com/bitcart/universalasync
Project-URL: Changelog, https://github.com/bitcart/universalasync/blob/master/CHANGELOG.md
Author-email: MrNaif2018 <chuff184@gmail.com>
License-Expression: MIT
License-File: LICENSE
Keywords: async,asyncio,asynctosync,await,bitcart,sync,synctoasync,universal
Classifier: Development Status :: 5 - Production/Stable
Classifier: Intended Audience :: Developers
Classifier: License :: OSI Approved :: MIT License
Classifier: Programming Language :: Python :: 3
Classifier: Programming Language :: Python :: 3.10
Classifier: Programming Language :: Python :: 3.11
Classifier: Programming Language :: Python :: 3.12
Classifier: Programming Language :: Python :: 3.13
Classifier: Programming Language :: Python :: 3.14
Classifier: Topic :: Software Development :: Libraries
Classifier: Topic :: Utilities
Requires-Python: >=3.10
